[
  {
    "autores": "MARTINS, LUANA ; PONTILLO, VALERIA ; COSTA, HEITOR ; FERRUCCI, FILOMENA ; PALOMBA, FABIO ; MACHADO, IVAN",
    "titulo": "Test code refactoring unveiled: where and how does it affect test code quality and effectiveness?",
    "revista": "EMPIRICAL SOFTWARE ENGINEERING",
    "volume": "30",
    "paginas": "1-39",
    "issn": "1382-3256",
    "ano": "2025",
    "link": "http://dx.doi.org/10.1007/s10664-024-10577-y",
    "qualis": "A1"
  },
  {
    "autores": "PONTILLO, V. ; MARTINS, L. A. ; MACHADO, IVAN C ; PALOMBA, F. ; FERRUCCI, F",
    "titulo": "An empirical investigation into the capabilities of anomaly detection approaches for test smell detection",
    "revista": "JOURNAL OF SYSTEMS AND SOFTWARE",
    "volume": "222",
    "paginas": "112320",
    "issn": "0164-1212",
    "ano": "2025",
    "link": "http://dx.doi.org/10.1016/j.jss.2024.112320",
    "qualis": "A1"
  },
  {
    "autores": "SANTANA, RAILANA ; MARTINS, LUANA ; VIRGÍNIO, TÁSSIO ; ROCHA, LARISSA ; COSTA, HEITOR ; MACHADO, IVAN",
    "titulo": "An empirical evaluation of RAIDE: A semi-automated approach for test smells detection and refactoring",
    "revista": "SCIENCE OF COMPUTER PROGRAMMING",
    "volume": "231",
    "paginas": "103013",
    "issn": "0167-6423",
    "ano": "2024",
    "link": "http://dx.doi.org/10.1016/j.scico.2023.103013",
    "qualis": "A4"
  },
  {
    "autores": "MARTINS, LUANA ; COSTA, HEITOR ; MACHADO, IVAN",
    "titulo": "On the diffusion of test smells and their relationship with test code quality of Java projects",
    "revista": "Journal of Software-Evolution and Process",
    "volume": "36",
    "paginas": "1-20",
    "issn": "2047-7473",
    "ano": "2047",
    "link": "http://dx.doi.org/10.1002/smr.2532",
    "qualis": "A4"
  },
  {
    "autores": "MARTINS, LUANA ; GHALEB, TAHER A. ; COSTA, HEITOR ; MACHADO, IVAN",
    "titulo": "A comprehensive catalog of refactoring strategies to handle test smells in Java-based systems",
    "revista": "SOFTWARE QUALITY JOURNAL",
    "volume": "32",
    "paginas": "64",
    "issn": "0963-9314",
    "ano": "2024",
    "link": "http://dx.doi.org/10.1007/s11219-024-09663-7",
    "qualis": "A2"
  },
  {
    "autores": "DAMASCENO, H. ; BEZERRA, C. I. M. ; SILVA, D. C. C. ; MACHADO, IVAN ; COUTINHO, E",
    "titulo": "Test smell refactoring revisited: What can internal quality attributes and developers? experience tell us?",
    "revista": "JOURNAL OF SOFTWARE ENGINEERING RESEARCH AND DEVELOPMENT",
    "volume": "11",
    "paginas": "1",
    "issn": "2195-1721",
    "ano": "2023",
    "link": "http://dx.doi.org/10.5753/jserd.2023.3195",
    "qualis": "A4"
  },
  {
    "autores": "SILVA, PÚBLIO ; BEZERRA, CARLA ; MACHADO, IVAN",
    "titulo": "Automating Feature Model maintainability evaluation using machine learning techniques",
    "revista": "JOURNAL OF SYSTEMS AND SOFTWARE",
    "volume": "195",
    "paginas": "111539",
    "issn": "0164-1212",
    "ano": "2023",
    "link": "http://dx.doi.org/10.1016/j.jss.2022.111539",
    "qualis": "A1"
  },
  {
    "autores": "KARITA, LEILA ; MOURAO, B. C. C. ; MARTINS, L. A. ; SOARES, L. R. ; MACHADO, I. C",
    "titulo": "Software industry awareness on green and sustainable software engineering: an extended survey",
    "revista": "JOURNAL OF SOFTWARE ENGINEERING RESEARCH AND DEVELOPMENT",
    "volume": "9",
    "paginas": "2",
    "issn": "2195-1721",
    "ano": "2021",
    "link": "http://dx.doi.org/10.5753/jserd.2021.742",
    "qualis": "A4"
  },
  {
    "autores": "SILVA JUNIOR, N. C. ; MARTINS, L. A. ; SOARES, L. R. ; COSTA, H. A. X. ; MACHADO, IVAN",
    "titulo": "How are test smells treated in the wild? A tale of two empirical studies",
    "revista": "JOURNAL OF SOFTWARE ENGINEERING RESEARCH AND DEVELOPMENT",
    "volume": "9",
    "paginas": "9",
    "issn": "2195-1721",
    "ano": "2021",
    "link": "http://dx.doi.org/10.5753/jserd.2021.1802",
    "qualis": "A4"
  },
  {
    "autores": "VIRGÍNIO, TÁSSIO ; SANTANA, RAILANA ; MARTINS, L. A. ; CRUZ, A. P. S. ; SOARES, L. R. ; COSTA, H. A. X. ; MACHADO, IVAN",
    "titulo": "On the test smells detection: an empirical study on the JNoseTest accuracy",
    "revista": "JOURNAL OF SOFTWARE ENGINEERING RESEARCH AND DEVELOPMENT",
    "volume": "9",
    "paginas": "8",
    "issn": "2195-1721",
    "ano": "2021",
    "link": "http://dx.doi.org/10.5753/jserd.2021.1893",
    "qualis": "A4"
  },
  {
    "autores": "MOTA JUNIOR, J. ; MACHADO, IVAN",
    "titulo": "Avaliação empírica de termos técnicos em issues de projetos opensource",
    "revista": "REVISTA ELETRÔNICA DE INICIAÇÃO CIENTÍFICA",
    "volume": "18",
    "paginas": "2",
    "issn": "1519-8219",
    "ano": "2020",
    "link": "http://dx.doi.org/10.5753/reic.2020.1744",
    "qualis": "C"
  },
  {
    "autores": "RODRIGUES SANTOS, ALCEMIR ; do Carmo Machado, Ivan ; SANTANA DE ALMEIDA, EDUARDO ; SIEGMUND, JANET ; APEL, SVEN",
    "titulo": "Comparing the influence of using feature-oriented programming and conditional compilation on comprehending feature-oriented software",
    "revista": "EMPIRICAL SOFTWARE ENGINEERING",
    "volume": "24",
    "paginas": "1226-1258",
    "issn": "1382-3256",
    "ano": "2019",
    "link": "http://dx.doi.org/10.1007/s10664-018-9658-x",
    "qualis": "A1"
  },
  {
    "autores": "LIMA, CRESCENCIO ; ASSUNÇÃO, WESLEY KG ; MARTINEZ, JABIER ; MENDONÇA, WILLIAM ; MACHADO, IVAN C ; CHAVEZ, CHRISTINA FG",
    "titulo": "Product line architecture recovery with outlier filtering in software families: the Apo-Games case study",
    "revista": "JOURNAL OF THE BRAZILIAN COMPUTER SOCIETY (IMPRESSO)",
    "volume": "25",
    "paginas": "1-17",
    "issn": "0104-6500",
    "ano": "2019",
    "link": "http://dx.doi.org/10.1186/s13173-019-0088-4",
    "qualis": "A2"
  },
  {
    "autores": "CARVALHO, M. L. L. ; SILVA, MATHEUS LESSA GONCALVES DA ; DA SILVA GOMES, GECYNALDA SOARES ; SANTOS, ALCEMIR RODRIGUES ; DO CARMO MACHADO, IVAN ; SOUZA, M. L. J. ; ALMEIDA, E. S",
    "titulo": "On the Implementation of Dynamic Software Product Lines: An Exploratory Study.",
    "revista": "JOURNAL OF SYSTEMS AND SOFTWARE",
    "volume": "136",
    "paginas": "74-100",
    "issn": "0164-1212",
    "ano": "2018",
    "link": "http://dx.doi.org/10.1016/j.jss.2017.11.004",
    "qualis": "A1"
  },
  {
    "autores": "SOARES, LARISSA ROCHA ; SCHOBBENS, PIERRE-YVES ; do Carmo Machado, Ivan ; de Almeida, Eduardo Santana",
    "titulo": "Feature interaction in software product line engineering: A systematic mapping study",
    "revista": "INFORMATION AND SOFTWARE TECHNOLOGY",
    "volume": "98",
    "paginas": "44-58",
    "issn": "0950-5849",
    "ano": "2018",
    "link": "http://dx.doi.org/10.1016/j.infsof.2018.01.016",
    "qualis": "A1"
  },
  {
    "autores": "CAVALCANTI, Y. C. ; MACHADO, I. C. ; SILVEIRA NETO, P. A. M. ; ALMEIDA, E. S",
    "titulo": "Towards Semi-automated Assignment of Software Change Requests",
    "revista": "The Journal of Systems and Software",
    "volume": "115",
    "paginas": "82-101",
    "issn": "0164-1212",
    "ano": "2016",
    "link": "http://dx.doi.org/10.1016/j.jss.2016.01.038",
    "qualis": "A1"
  },
  {
    "autores": "MACHADO, I. C. ; CAVALCANTI, Y. C. ; MCGREGOR, J ; Almeida, Eduardo S",
    "titulo": "On Strategies for Testing Software Product Lines: A Systematic Literature Review",
    "revista": "INFORMATION AND SOFTWARE TECHNOLOGY",
    "volume": "56",
    "paginas": "1183",
    "issn": "0950-5849",
    "ano": "2014",
    "link": "http://dx.doi.org/10.1016/j.infsof.2014.04.002",
    "qualis": "A1"
  },
  {
    "autores": "CAVALCANTI, Y. C. ; NETO, P. A. M. S. ; MACHADO, I. C. ; VALE, T. ; ALMEIDA, E. S. ; MEIRA, Silvio Romero de Lemos",
    "titulo": "Challenges and opportunities for software change request repositories: a systematic mapping study",
    "revista": "J SOFTW-EVOL PROC",
    "volume": "26",
    "paginas": "620-653",
    "issn": "2047-7481",
    "ano": "2047",
    "link": "http://dx.doi.org/10.1002/smr.1639",
    "qualis": "A4"
  },
  {
    "autores": "SOUZA, IURI SANTOS ; DA SILVA GOMES, GECYNALDA SOARES ; DA MOTA SILVEIRA NETO, PAULO ANSELMO ; DO CARMO MACHADO, IVAN ; DE ALMEIDA, EDUARDO SANTANA ; DE LEMOS MEIRA, SILVIO ROMERO",
    "titulo": "Evidence of Software Inspection on Feature Specification for Software Product Lines",
    "revista": "The Journal of Systems and Software",
    "volume": "86",
    "paginas": "1172-1190",
    "issn": "0164-1212",
    "ano": "2013",
    "link": "http://dx.doi.org/10.1016/j.jss.2012.11.044",
    "qualis": "A1"
  },
  {
    "autores": "LOBATO, LUANNA LOPES ; BITTAR, THIAGO JABUR ; Neto, Paulo Anselmo da Mota Silveira ; MACHADO, Ivan Do Carmo ; de Almeida, Eduardo Santana ; Meira, Silvio Romero de Lemos",
    "titulo": "RISK MANAGEMENT IN SOFTWARE PRODUCT LINE ENGINEERING: A MAPPING STUDY",
    "revista": "International Journal of Software Engineering and Knowledge Engineering",
    "volume": "23",
    "paginas": "523-558",
    "issn": "0218-1940",
    "ano": "2013",
    "link": "http://dx.doi.org/10.1142/S0218194013500150",
    "qualis": "B1"
  },
  {
    "autores": "WOHLIN, CLAES ; RUNESON, PER ; da Mota Silveira Neto, Paulo Anselmo ; ENGSTRÖM, EMELIE ; do Carmo Machado, Ivan ; de Almeida, Eduardo Santana",
    "titulo": "On the reliability of mapping studies in software engineering",
    "revista": "The Journal of Systems and Software",
    "volume": "86",
    "paginas": "2594-2610",
    "issn": "0164-1212",
    "ano": "2013",
    "link": "http://dx.doi.org/10.1016/j.jss.2013.04.076",
    "qualis": "A1"
  },
  {
    "autores": "MACHADO, I. C. ; MCGREGOR, J ; ALMEIDA, E. S",
    "titulo": "Strategies for Testing Products in Software Product Lines",
    "revista": "SOFTWARE ENGINEERING NOTES",
    "volume": "37",
    "paginas": "1-8",
    "issn": "0163-5948",
    "ano": "2012",
    "link": "http://dx.doi.org/10.1145/2382756.2382783",
    "qualis": "C"
  },
  {
    "autores": "NETO, P. A. M. S. ; MACHADO, I. C. ; MCGREGOR, J ; MEIRA, Silvio Romero de Lemos ; ALMEIDA, E. S",
    "titulo": "A systematic mapping study of software product lines testing",
    "revista": "INFORMATION AND SOFTWARE TECHNOLOGY",
    "volume": "53",
    "paginas": "407-423",
    "issn": "0950-5849",
    "ano": "2011",
    "link": "http://dx.doi.org/10.1016/j.infsof.2010.12.003",
    "qualis": "A1"
  },
  {
    "autores": "NETO, P. A. M. S. ; ENGSTROM, E. ; MACHADO, I. C. ; ALMEIDA, E. S. ; RUNERSON, P ; MEIRA, Silvio Romero de Lemos",
    "titulo": "Testing Software Product Lines",
    "revista": "IEEE SOFTWARE",
    "volume": "28",
    "paginas": "16-21",
    "issn": "0740-7459",
    "ano": "2011",
    "link": "http://dx.doi.org/10.1109/MS.2011.90",
    "qualis": "A2"
  }
]